hcam_obsutils/__init__.py
hcam_obsutils/data/hcam_flux_stds.csv
hcam_obsutils/data/sdss_flux_stds.csv
hcam_obsutils/data/ucam_cube_flux_stds.csv
hcam_obsutils/data/ucam_flux_stds.csv
hcam_obsutils/dbutils/__init__.py
hcam_obsutils/formats/__init__.py
hcam_obsutils/qcutils/__init__.py
hcam_obsutils/qcutils/gain.py
hcam_obsutils/scripts/__init__.py
hcam_obsutils/scripts/missbias.py
hcam_obsutils/scripts/unique.py
hcam_obsutils/scripts/ucam/ucam_zeropoints.py
hcam_obsutils/scripts/ucam/qc/gain.py
hcam_obsutils/scripts/ucam/qc/gain_simple.py
hcam_obsutils/scripts/ucam/qc/qc.py
hcam_obsutils/scripts/uspec/qc.py
hcam_obsutils/scripts/uspec/uspec_zeropoints.py
hcam_obsutils/throughput/__init__.py
hcam_obsutils-0.0.6.dist-info/METADATA
hcam_obsutils-0.0.6.dist-info/WHEEL
hcam_obsutils-0.0.6.dist-info/entry_points.txt
hcam_obsutils-0.0.6.dist-info/licenses/LICENSE
hcam_obsutils-0.0.6.dist-info/RECORD
