Metadata-Version: 2.4
Name: hcam_obsutils
Version: 0.0.6
Summary: A collection of utility scripts for observing with HiPERCAM and ULTRACAM.
Project-URL: Homepage, https://github.com/hipercam/hcam_obsutils
Project-URL: Issues, https://github.com/hipercam/hcam_obsutils/issues
Author-email: Stuart Littlefair <s.littlefair@sheffield.ac.uk>, Martin Dyer <m.j.dyer@sheffield.ac.uk>
License-Expression: MIT
License-File: LICENSE
Classifier: Operating System :: OS Independent
Classifier: Programming Language :: Python :: 3
Requires-Python: >=3.9
Requires-Dist: astropy
Requires-Dist: numpy
Requires-Dist: scikit-image
Requires-Dist: scipy
Requires-Dist: sigfig
Requires-Dist: thefuzz
Requires-Dist: trm-cline
